lt_env/__init__.py
lt_env-0.0.1.dist-info/METADATA
lt_env-0.0.1.dist-info/WHEEL
lt_env-0.0.1.dist-info/top_level.txt
lt_env-0.0.1.dist-info/RECORD
