Metadata-Version: 2.1
Name: lt-env
Version: 0.0.1
Summary: A OpenAI Gym Env for gym
Requires-Dist: gym
